{"unique_symbols": {"gammaI": 0.1, "True": 1.0, "cD": 1.4, "gammaD": 0.1499777408107083, "Inf": Infinity, "R0": 0.0, "NAN": NaN, "theta": 0.15995349035142684, "inf": Infinity, "A0": 1.2, "None": null, "epsilonA": 0.003696260295351006, "dD": 0.010050054796593856, "gammaA": 0.14539072799026018, "Q0": 372.59999999999997, "sigma": 0.14285714285714285, "pi": 3.141592653589793, "rho": 0.12, "D0": 1.0, "epsilonI": 0.10009989884812746, "little_endian": 1.0, "dI": 0.014070076715231397, "E0": 3.0, "day": 55.0, "erfc": {"__class__": "Callable", "__name__": "erfc", "pyversion": "3.6", "value": null, "importer": "scipy.special"}, "p": 0.042927917364962494, "I0": 1.8, "infty": Infinity, "e": 2.718281828459045, "wofz": {"__class__": "Callable", "__name__": "wofz", "pyversion": "3.6", "value": null, "importer": "scipy.special"}, "erf": {"__class__": "Callable", "__name__": "erf", "pyversion": "3.6", "value": null, "importer": "lmfit.confidence"}, "delta": 0.0003929841414919144, "S0": 313120.2591492884, "gamfcn": {"__class__": "Callable", "__name__": "gamma", "pyversion": "3.6", "value": null, "importer": "scipy.special"}, "newaxis": null, "lambda0": 0.018518518518518517, "False": 0.0, "nan": NaN, "beta": 7.474098209949121e-06}, "params": [["beta", 7.474098209949121e-06, true, null, 0, 1e-05, null, null, null, 7.474098209949121e-06, null], ["theta", 0.15995349035142684, true, null, 0.1, 0.16, null, null, null, 0.15995349035142684, null], ["p", 0.042927917364962494, true, null, 0.001, 0.33, null, null, null, 0.042927917364962494, null], ["lambda0", 0.018518518518518517, false, null, -Infinity, Infinity, null, null, null, 0.018518518518518517, null], ["sigma", 0.14285714285714285, false, null, 0, Infinity, null, null, null, 0.14285714285714285, null], ["rho", 0.12, false, null, 0, Infinity, null, null, null, 0.12, null], ["epsilonA", 0.003696260295351006, true, null, 0, 0.2, null, null, null, 0.003696260295351006, null], ["epsilonI", 0.10009989884812746, true, null, 0.1, 0.4, null, null, null, 0.10009989884812746, null], ["gammaA", 0.14539072799026018, true, null, 0.1, 0.15, null, null, null, 0.14539072799026018, null], ["gammaI", 0.1, false, null, 0, Infinity, null, null, null, 0.1, null], ["gammaD", 0.1499777408107083, true, null, 0.1, 0.15, null, null, null, 0.1499777408107083, null], ["cD", 1.4, true, null, 1.1, 1.7, null, null, null, 1.4, null], ["dD", 0.010050054796593856, false, "gammaD*0.06280193236714976/(1-0.06280193236714976)", -Infinity, Infinity, null, null, null, 0.010050054796593856, null], ["dI", 0.014070076715231397, false, "cD*dD", -Infinity, Infinity, null, null, null, 0.014070076715231397, null], ["delta", 0.0003929841414919144, true, null, 0, 1.0, null, null, null, 0.0003929841414919144, null], ["day", 55, false, null, 0, Infinity, null, null, null, 55, null], ["S0", 313120.2591492884, true, null, 745.1999999999999, 7650154.0, null, null, null, 313120.2591492884, null], ["Q0", 372.59999999999997, false, null, 0, Infinity, null, null, null, 372.59999999999997, null], ["E0", 3.0, false, null, 0, Infinity, null, null, null, 3.0, null], ["A0", 1.2, false, null, 0, Infinity, null, null, null, 1.2, null], ["I0", 1.8, false, null, 0, Infinity, null, null, null, 1.8, null], ["D0", 1, false, null, 0, Infinity, null, null, null, 1, null], ["R0", 0, false, null, -Infinity, Infinity, null, null, null, 0, null]]}