{"unique_symbols": {"I0": 1.8, "NAN": NaN, "wofz": {"__class__": "Callable", "__name__": "wofz", "pyversion": "3.6", "value": null, "importer": "scipy.special"}, "False": 0.0, "epsilonI": 0.3969397940542513, "day": 93.0, "epsilonA": 0.1999999464810646, "delta": 0.00020905057542164318, "D0": 1, "e": 2.718281828459045, "Inf": Infinity, "newaxis": null, "A0": 1.2, "little_endian": 1.0, "infty": Infinity, "dI": 0.004301553198954813, "gammaD": 0.13412810112125587, "None": null, "erf": {"__class__": "Callable", "__name__": "erf", "pyversion": "3.6", "value": null, "importer": "lmfit.confidence"}, "R0": 0.0, "True": 1.0, "gamfcn": {"__class__": "Callable", "__name__": "gamma", "pyversion": "3.6", "value": null, "importer": "scipy.special"}, "E0": 3.0, "nan": NaN, "gammaI": 0.1, "theta": 0.1430093310420449, "gammaA": 0.10977009429427421, "erfc": {"__class__": "Callable", "__name__": "erfc", "pyversion": "3.6", "value": null, "importer": "scipy.special"}, "S0": 104440.72869807601, "pi": 3.141592653589793, "lambda0": 0.010752688172043012, "p": 0.3299993924522606, "inf": Infinity, "beta": 9.999250044990629e-06, "dD": 0.003072537999253438, "sigma": 0.14285714285714285, "rho": 0.12, "Q0": 696.6, "cD": 1.4}, "params": [["beta", 9.999250044990629e-06, true, null, 0, 1e-05, null, null, null, 5.198475829561383e-07, null], ["theta", 0.1430093310420449, true, null, 0.1, 0.16, null, null, null, 0.10380962216487101, null], ["p", 0.3299993924522606, true, null, 0.001, 0.33, null, null, null, 0.32999730182877024, null], ["sigma", 0.14285714285714285, false, null, 0, Infinity, null, null, null, 0.14285714285714285, null], ["rho", 0.12, false, null, 0, Infinity, null, null, null, 0.12, null], ["epsilonA", 0.1999999464810646, true, null, 0, 0.2, null, null, null, 0.11740562095669867, null], ["epsilonI", 0.3969397940542513, true, null, 0.1, 0.4, null, null, null, 0.3997823676915152, null], ["lambda0", 0.010752688172043012, false, null, -Infinity, Infinity, null, null, null, 0.010752688172043012, null], ["gammaA", 0.10977009429427421, true, null, 0.1, 0.15, null, null, null, 0.149999918707317, null], ["gammaI", 0.1, false, null, 0, Infinity, null, null, null, 0.1, null], ["gammaD", 0.13412810112125587, true, null, 0.1, 0.15, null, null, null, 0.14998227872264114, null], ["cD", 1.4, true, null, 1.1, 1.7, null, null, null, 1.4, null], ["dD", 0.003072537999253438, false, "gammaD*0.02239448751076658/(1-0.02239448751076658)", -Infinity, Infinity, null, null, null, 0.003435717398051691, null], ["dI", 0.004301553198954813, false, "cD*dD", -Infinity, Infinity, null, null, null, 0.004810004357272367, null], ["delta", 0.00020905057542164318, true, null, 0, 1.0, null, null, null, 7.850766196210168e-05, null], ["S0", 104440.72869807601, true, null, 1393.2, 6848925.0, null, null, null, 1393.2, null], ["R0", 0, false, null, -Infinity, Infinity, null, null, null, 0, null], ["Q0", 696.6, false, null, 0, Infinity, null, null, null, 696.6, null], ["E0", 3.0, false, null, 0, Infinity, null, null, null, 3.0, null], ["A0", 1.2, false, null, 0, Infinity, null, null, null, 1.2, null], ["I0", 1.8, false, null, 0, Infinity, null, null, null, 1.8, null], ["day", 93, false, null, 0, Infinity, null, null, null, 93, null], ["D0", 1, false, null, 0, Infinity, null, null, null, 1, null]]}