{"unique_symbols": {"erfc": {"__class__": "Callable", "__name__": "erfc", "pyversion": "3.6", "value": null, "importer": "scipy.special"}, "inf": Infinity, "Inf": Infinity, "D0": 1, "True": 1.0, "infty": Infinity, "I0": 1.8, "wofz": {"__class__": "Callable", "__name__": "wofz", "pyversion": "3.6", "value": null, "importer": "scipy.special"}, "newaxis": null, "gammaD": 0.10000796283198617, "False": 0.0, "theta": 0.15326315320339212, "sigma": 0.14285714285714285, "erf": {"__class__": "Callable", "__name__": "erf", "pyversion": "3.6", "value": null, "importer": "lmfit.confidence"}, "beta": 4.299832921028355e-06, "Q0": 399.59999999999997, "e": 2.718281828459045, "delta": 0.043305434079460525, "R0": 0.0, "dD": 0.006731305190614453, "gamfcn": {"__class__": "Callable", "__name__": "gamma", "pyversion": "3.6", "value": null, "importer": "scipy.special"}, "gammaA": 0.10000002117416684, "rho": 0.12, "cD": 1.4, "S0": 1915.5365568725242, "epsilonA": 0.04055961325612976, "dI": 0.009423827266860233, "A0": 1.2, "lambda0": 0.011235955056179775, "None": null, "p": 0.05797412982391406, "NAN": NaN, "pi": 3.141592653589793, "E0": 3.0, "little_endian": 1.0, "nan": NaN, "gammaI": 0.1, "epsilonI": 0.3926970501210685, "day": 89.0}, "params": [["beta", 4.299832921028355e-06, true, null, 0, 1e-05, null, null, null, 9.33e-08, null], ["theta", 0.15326315320339212, true, null, 0.1, 0.16, null, null, null, 0.129598, null], ["p", 0.05797412982391406, true, null, 0.001, 0.33, null, null, null, 0.15, null], ["sigma", 0.14285714285714285, false, null, 0, Infinity, null, null, null, 0.14285714285714285, null], ["rho", 0.12, false, null, 0, Infinity, null, null, null, 0.12, null], ["epsilonA", 0.04055961325612976, true, null, 0, 0.2, null, null, null, 0, null], ["epsilonI", 0.3926970501210685, true, null, 0.1, 0.4, null, null, null, 0.2, null], ["lambda0", 0.011235955056179775, false, null, -Infinity, Infinity, null, null, null, 0.011235955056179775, null], ["gammaA", 0.10000002117416684, true, null, 0.1, 0.15, null, null, null, 0.13, null], ["gammaI", 0.1, false, null, 0, Infinity, null, null, null, 0.1, null], ["gammaD", 0.10000796283198617, true, null, 0.1, 0.15, null, null, null, 0.12, null], ["cD", 1.4, true, null, 1.1, 1.7, null, null, null, 1.4, null], ["dD", 0.006731305190614453, false, "gammaD*0.06306306306306306/(1-0.06306306306306306)", -Infinity, Infinity, null, null, null, 0.008076923076923075, null], ["dI", 0.009423827266860233, false, "cD*dD", -Infinity, Infinity, null, null, null, 0.011307692307692305, null], ["delta", 0.043305434079460525, true, null, 0, 1.0, null, null, null, 0.0001, null], ["S0", 1915.5365568725242, true, null, 799.1999999999999, 33785.0, null, null, null, 799.1999999999999, null], ["R0", 0, false, null, -Infinity, Infinity, null, null, null, 0, null], ["Q0", 399.59999999999997, false, null, 0, Infinity, null, null, null, 399.59999999999997, null], ["E0", 3.0, false, null, 0, Infinity, null, null, null, 3.0, null], ["A0", 1.2, false, null, 0, Infinity, null, null, null, 1.2, null], ["I0", 1.8, false, null, 0, Infinity, null, null, null, 1.8, null], ["day", 89, false, null, 0, Infinity, null, null, null, 89, null], ["D0", 1, false, null, 0, Infinity, null, null, null, 1, null]]}