{"unique_symbols": {"theta": 0.15995014224369702, "S0": 40445.25357099194, "dI": 0.013883529300450446, "erfc": {"__class__": "Callable", "__name__": "erfc", "pyversion": "3.6", "value": null, "importer": "scipy.special"}, "Q0": 1461.0, "inf": Infinity, "nan": NaN, "p": 0.16849613432819363, "little_endian": 1.0, "R0": 0.0, "gammaA": 0.10000006170099522, "infty": Infinity, "gammaD": 0.14999990975510322, "epsilonA": 5.551115123125783e-17, "NAN": NaN, "erf": {"__class__": "Callable", "__name__": "erf", "pyversion": "3.6", "value": null, "importer": "lmfit.confidence"}, "lambda0": 0.012987012987012988, "I0": 3.6, "e": 2.718281828459045, "None": null, "gamfcn": {"__class__": "Callable", "__name__": "gamma", "pyversion": "3.6", "value": null, "importer": "scipy.special"}, "D0": 2, "wofz": {"__class__": "Callable", "__name__": "wofz", "pyversion": "3.6", "value": null, "importer": "scipy.special"}, "Inf": Infinity, "dD": 0.00991680664317889, "gammaI": 0.1, "E0": 6.0, "False": 0.0, "pi": 3.141592653589793, "epsilonI": 0.39999999806065445, "day": 77.0, "sigma": 0.14285714285714285, "delta": 0.017435878266294058, "A0": 2.4, "True": 1.0, "cD": 1.4, "rho": 0.12, "newaxis": null, "beta": 9.99999999995844e-06}, "params": [["beta", 9.99999999995844e-06, true, null, 0, 1e-05, null, null, null, 9.999998797008523e-06, null], ["theta", 0.15995014224369702, true, null, 0.1, 0.16, null, null, null, 0.15490762923355825, null], ["p", 0.16849613432819363, true, null, 0.001, 0.33, null, null, null, 0.32999998626016597, null], ["sigma", 0.14285714285714285, false, null, 0, Infinity, null, null, null, 0.14285714285714285, null], ["rho", 0.12, false, null, 0, Infinity, null, null, null, 0.12, null], ["epsilonA", 5.551115123125783e-17, true, null, 0, 0.2, null, null, null, 0.19999999994430945, null], ["epsilonI", 0.39999999806065445, true, null, 0.1, 0.4, null, null, null, 0.3999896980451353, null], ["lambda0", 0.012987012987012988, false, null, -Infinity, Infinity, null, null, null, 0.012987012987012988, null], ["gammaA", 0.10000006170099522, true, null, 0.1, 0.15, null, null, null, 0.14943260666491953, null], ["gammaI", 0.1, false, null, 0, Infinity, null, null, null, 0.1, null], ["gammaD", 0.14999990975510322, true, null, 0.1, 0.15, null, null, null, 0.14484292749193012, null], ["cD", 1.4, true, null, 1.1, 1.7, null, null, null, 1.4, null], ["dD", 0.00991680664317889, false, "gammaD*0.06201232032854209/(1-0.06201232032854209)", -Infinity, Infinity, null, null, null, 0.009575867798284347, null], ["dI", 0.013883529300450446, false, "cD*dD", -Infinity, Infinity, null, null, null, 0.013406214917598084, null], ["delta", 0.017435878266294058, true, null, 0, 1.0, null, null, null, 0.0011849257225726162, null], ["S0", 40445.25357099194, true, null, 2922.0, 3323929.0, null, null, null, 2922.0, null], ["R0", 0, false, null, -Infinity, Infinity, null, null, null, 0, null], ["Q0", 1461.0, false, null, 0, Infinity, null, null, null, 1461.0, null], ["E0", 6.0, false, null, 0, Infinity, null, null, null, 6.0, null], ["A0", 2.4, false, null, 0, Infinity, null, null, null, 2.4, null], ["I0", 3.6, false, null, 0, Infinity, null, null, null, 3.6, null], ["day", 77, false, null, 0, Infinity, null, null, null, 77, null], ["D0", 2, false, null, 0, Infinity, null, null, null, 2, null]]}